{"id":111,"season":2000,"round":5,"ladder":[{"stats":{"played":5,"wins":4,"drawn":1,"lost":0,"byes":2,"points for":108,"points against":72,"points difference":36,"home record":"0 - 0","away record":"0 - 0","points":13,"streak":"","form":" - ","average losing margin":0,"average winning margin":9,"golden point":0,"close games":2,"day record":"0-0-0","players used":21},"teamNickName":"Broncos","clubProfileUrl":"\/clubs\/brisbane-broncos\/","theme":{"key":"broncos","logoVariants":["badge-light.png","badge-light.svg","badge.png","badge.svg","silhouette.png","silhouette.svg","text.svg"]},"movement":"none","nextTeam":{"fullName":"North Queensland Cowboys","teamId":500012,"nickName":"Cowboys","theme":{"key":"cowboys","logoVariants":["badge-light.png","badge-light.svg","badge.png","badge.svg","silhouette.png","silhouette.svg","text.svg"]},"matchCentreUrl":"\/draw\/nrl-premiership\/2000\/round-6\/cowboys-vs-broncos\/"}},{"stats":{"played":5,"wins":4,"drawn":0,"lost":0,"byes":2,"points for":118,"points against":52,"points difference":66,"home record":"0 - 0","away record":"0 - 0","points":12,"streak":"","form":" - ","average losing margin":8,"average winning margin":18,"golden point":0,"close games":1,"day record":"0-0-0","players used":23},"teamNickName":"Raiders","clubProfileUrl":"\/clubs\/canberra-raiders\/","theme":{"key":"raiders","logoVariants":["badge.png","badge.svg","silhouette.png","silhouette.svg","text.svg"]},"movement":"up","nextTeam":{"fullName":"Newcastle Knights","teamId":500003,"nickName":"Knights","theme":{"key":"knights","logoVariants":["badge-light.png","badge-light.svg","badge.png","badge.svg","silhouette.png","silhouette.svg","text.svg"]},"matchCentreUrl":"\/draw\/nrl-premiership\/2000\/round-6\/knights-vs-raiders\/"}},{"stats":{"played":5,"wins":3,"drawn":1,"lost":0,"byes":2,"points for":89,"points against":106,"points difference":-17,"home record":"0 - 0","away record":"0 - 0","points":11,"streak":"","form":" - ","average losing margin":19,"average winning margin":7,"golden point":0,"close games":1,"day record":"0-0-0","players used":23},"teamNickName":"Wests Tigers","clubProfileUrl":"\/clubs\/wests-tigers\/","theme":{"key":"wests-tigers","logoVariants":["badge-light.png","badge-light.svg","badge.png","badge.svg","silhouette.png","silhouette.svg","text.svg"]},"movement":"up","nextTeam":{"fullName":"St. George Illawarra Dragons","teamId":500022,"nickName":"Dragons","theme":{"key":"dragons","logoVariants":["badge.png","badge.svg","silhouette.png","silhouette.svg","text.svg"]},"matchCentreUrl":"\/draw\/nrl-premiership\/2000\/round-6\/dragons-vs-wests-tigers\/"}},{"stats":{"played":5,"wins":3,"drawn":0,"lost":0,"byes":2,"points for":114,"points against":63,"points difference":51,"home record":"0 - 0","away record":"0 - 0","points":10,"streak":"","form":" - ","average losing margin":2,"average winning margin":18,"golden point":1,"close games":2,"day record":"1-0-0","players used":22},"teamNickName":"Sharks","clubProfileUrl":"\/clubs\/cronulla-sutherland-sharks\/","theme":{"key":"sharks","logoVariants":["badge-light.png","badge-light.svg","badge.png","badge.svg","silhouette.png","silhouette.svg","text.svg"]},"movement":"up","nextTeam":{"fullName":"Canterbury-Bankstown Bulldogs","teamId":500010,"nickName":"Bulldogs","theme":{"key":"bulldogs","logoVariants":["badge.png","badge.svg","silhouette.png","silhouette.svg","text.svg"]},"matchCentreUrl":"\/draw\/nrl-premiership\/2000\/round-6\/sharks-vs-bulldogs\/"}},{"stats":{"played":5,"wins":3,"drawn":0,"lost":0,"byes":2,"points for":101,"points against":77,"points difference":24,"home record":"0 - 0","away record":"0 - 0","points":10,"streak":"","form":" - ","average losing margin":11,"average winning margin":15,"golden point":0,"close games":0,"day record":"0-0-0","players used":23},"teamNickName":"Panthers","clubProfileUrl":"\/clubs\/penrith-panthers\/","theme":{"key":"panthers","logoVariants":["badge-light.png","badge-light.svg","badge.png","badge.svg","silhouette.png","silhouette.svg","text.svg"]},"movement":"down","nextTeam":{"fullName":"Warriors","teamId":500032,"nickName":"Warriors","theme":{"key":"warriors","logoVariants":["badge.png","badge.svg","silhouette.png","silhouette.svg","text.svg"]},"matchCentreUrl":"\/draw\/nrl-premiership\/2000\/round-6\/panthers-vs-warriors\/"}},{"stats":{"played":5,"wins":3,"drawn":0,"lost":0,"byes":2,"points for":80,"points against":64,"points difference":16,"home record":"0 - 0","away record":"0 - 0","points":10,"streak":"","form":" - ","average losing margin":19,"average winning margin":18,"golden point":1,"close games":0,"day record":"0-0-0","players used":25},"teamNickName":"Bulldogs","clubProfileUrl":"\/clubs\/canterbury-bankstown-bulldogs\/","theme":{"key":"bulldogs","logoVariants":["badge.png","badge.svg","silhouette.png","silhouette.svg","text.svg"]},"movement":"up","nextTeam":{"fullName":"Cronulla-Sutherland Sharks","teamId":500028,"nickName":"Sharks","theme":{"key":"sharks","logoVariants":["badge-light.png","badge-light.svg","badge.png","badge.svg","silhouette.png","silhouette.svg","text.svg"]},"matchCentreUrl":"\/draw\/nrl-premiership\/2000\/round-6\/sharks-vs-bulldogs\/"}},{"stats":{"played":5,"wins":3,"drawn":0,"lost":0,"byes":2,"points for":88,"points against":90,"points difference":-2,"home record":"0 - 0","away record":"0 - 0","points":10,"streak":"","form":" - ","average losing margin":23,"average winning margin":14,"golden point":0,"close games":1,"day record":"1-0-0","players used":24},"teamNickName":"Roosters","clubProfileUrl":"\/clubs\/sydney-roosters\/","theme":{"key":"roosters","logoVariants":["badge.png","badge.svg","silhouette.png","silhouette.svg","text.svg"]},"movement":"up","nextTeam":{"fullName":"Melbourne Storm","teamId":500021,"nickName":"Storm","theme":{"key":"storm","logoVariants":["badge-light.png","badge-light.svg","badge.png","badge.svg","silhouette.png","silhouette.svg","text.svg"]},"matchCentreUrl":"\/draw\/nrl-premiership\/2000\/round-6\/storm-vs-roosters\/"}},{"stats":{"played":5,"wins":3,"drawn":0,"lost":0,"byes":2,"points for":82,"points against":94,"points difference":-12,"home record":"0 - 0","away record":"0 - 0","points":10,"streak":"","form":" - ","average losing margin":17,"average winning margin":7,"golden point":0,"close games":1,"day record":"0-0-0","players used":21},"teamNickName":"Eagles","theme":{"key":"eagles"},"movement":"down","nextTeam":{"teamId":0}},{"stats":{"played":5,"wins":2,"drawn":1,"lost":0,"byes":2,"points for":130,"points against":76,"points difference":54,"home record":"0 - 0","away record":"0 - 0","points":9,"streak":"","form":" - ","average losing margin":5,"average winning margin":35,"golden point":0,"close games":1,"day record":"0-0-0","players used":22},"teamNickName":"Knights","clubProfileUrl":"\/clubs\/newcastle-knights\/","theme":{"key":"knights","logoVariants":["badge-light.png","badge-light.svg","badge.png","badge.svg","silhouette.png","silhouette.svg","text.svg"]},"movement":"down","nextTeam":{"fullName":"Canberra Raiders","teamId":500013,"nickName":"Raiders","theme":{"key":"raiders","logoVariants":["badge.png","badge.svg","silhouette.png","silhouette.svg","text.svg"]},"matchCentreUrl":"\/draw\/nrl-premiership\/2000\/round-6\/knights-vs-raiders\/"}},{"stats":{"played":5,"wins":1,"drawn":1,"lost":0,"byes":2,"points for":70,"points against":125,"points difference":-55,"home record":"0 - 0","away record":"0 - 0","points":7,"streak":"","form":" - ","average losing margin":15,"average winning margin":8,"golden point":0,"close games":1,"day record":"0-0-0","players used":23},"teamNickName":"Warriors","clubProfileUrl":"\/clubs\/warriors\/","theme":{"key":"warriors","logoVariants":["badge.png","badge.svg","silhouette.png","silhouette.svg","text.svg"]},"movement":"none","nextTeam":{"fullName":"Penrith Panthers","teamId":500014,"nickName":"Panthers","theme":{"key":"panthers","logoVariants":["badge-light.png","badge-light.svg","badge.png","badge.svg","silhouette.png","silhouette.svg","text.svg"]},"matchCentreUrl":"\/draw\/nrl-premiership\/2000\/round-6\/panthers-vs-warriors\/"}},{"stats":{"played":5,"wins":1,"drawn":0,"lost":0,"byes":2,"points for":116,"points against":108,"points difference":8,"home record":"0 - 0","away record":"0 - 0","points":6,"streak":"","form":" - ","average losing margin":13,"average winning margin":60,"golden point":0,"close games":1,"day record":"0-0-0","players used":19},"teamNickName":"Storm","clubProfileUrl":"\/clubs\/melbourne-storm\/","theme":{"key":"storm","logoVariants":["badge-light.png","badge-light.svg","badge.png","badge.svg","silhouette.png","silhouette.svg","text.svg"]},"movement":"up","nextTeam":{"fullName":"Sydney Roosters","teamId":500001,"nickName":"Roosters","theme":{"key":"roosters","logoVariants":["badge.png","badge.svg","silhouette.png","silhouette.svg","text.svg"]},"matchCentreUrl":"\/draw\/nrl-premiership\/2000\/round-6\/storm-vs-roosters\/"}},{"stats":{"played":5,"wins":1,"drawn":0,"lost":0,"byes":2,"points for":75,"points against":104,"points difference":-29,"home record":"0 - 0","away record":"0 - 0","points":6,"streak":"","form":" - ","average losing margin":7,"average winning margin":1,"golden point":0,"close games":2,"day record":"0-0-1","players used":23},"teamNickName":"Eels","clubProfileUrl":"\/clubs\/parramatta-eels\/","theme":{"key":"eels","logoVariants":["badge.png","badge.svg","silhouette.png","silhouette.svg","text.svg"]},"movement":"down","nextTeam":{"fullName":"Northern Eagles","teamId":10053,"nickName":"Eagles","theme":{"key":"eagles"},"matchCentreUrl":"\/draw\/nrl-premiership\/2000\/round-6\/eels-vs-eagles\/"}},{"stats":{"played":5,"wins":1,"drawn":0,"lost":0,"byes":2,"points for":62,"points against":107,"points difference":-45,"home record":"0 - 0","away record":"0 - 0","points":6,"streak":"","form":" - ","average losing margin":13,"average winning margin":8,"golden point":0,"close games":1,"day record":"0-0-0","players used":29},"teamNickName":"Cowboys","clubProfileUrl":"\/clubs\/north-queensland-cowboys\/","theme":{"key":"cowboys","logoVariants":["badge-light.png","badge-light.svg","badge.png","badge.svg","silhouette.png","silhouette.svg","text.svg"]},"movement":"down","nextTeam":{"fullName":"Brisbane Broncos","teamId":500011,"nickName":"Broncos","theme":{"key":"broncos","logoVariants":["badge-light.png","badge-light.svg","badge.png","badge.svg","silhouette.png","silhouette.svg","text.svg"]},"matchCentreUrl":"\/draw\/nrl-premiership\/2000\/round-6\/cowboys-vs-broncos\/"}},{"stats":{"played":5,"wins":1,"drawn":0,"lost":0,"byes":2,"points for":54,"points against":149,"points difference":-95,"home record":"0 - 0","away record":"0 - 0","points":6,"streak":"","form":" - ","average losing margin":25,"average winning margin":6,"golden point":2,"close games":2,"day record":"0-0-1","players used":21},"teamNickName":"Dragons","clubProfileUrl":"\/clubs\/st-george-illawarra-dragons\/","theme":{"key":"dragons","logoVariants":["badge.png","badge.svg","silhouette.png","silhouette.svg","text.svg"]},"movement":"down","nextTeam":{"fullName":"Wests Tigers","teamId":500023,"nickName":"Wests Tigers","theme":{"key":"wests-tigers","logoVariants":["badge-light.png","badge-light.svg","badge.png","badge.svg","silhouette.png","silhouette.svg","text.svg"]},"matchCentreUrl":"\/draw\/nrl-premiership\/2000\/round-6\/dragons-vs-wests-tigers\/"}}]}