{"id":113,"season":2017,"round":11,"ladder":[{"stats":{"played":11,"wins":9,"drawn":1,"lost":1,"byes":0,"points for":323,"points against":166,"points difference":157,"home record":"5 - 0","away record":"4 - 1","points":19,"streak":"1D","form":"4 - 0","average losing margin":22,"average winning margin":19.9,"golden point":0,"close games":2,"day record":"8-1-1","night record":"1-0-0","players used":29},"teamNickName":"Roos","theme":{"key":"roos","logoVariants":["badge.png","silhouette.png"]},"movement":"none","nextTeam":{"fullName":"Mounties","teamId":500137,"nickName":"Mounties","theme":{"key":"mounties","logoVariants":["badge-light.png","badge-light.svg","badge.png","badge.svg","silhouette.png","silhouette.svg"]},"matchCentreUrl":"https:\/\/www.nswrl.com.au\/draw\/intrust-super-premiership\/2017\/round-12\/mounties-vs-roos\/"}},{"stats":{"played":11,"wins":8,"drawn":2,"lost":1,"byes":0,"points for":309,"points against":196,"points difference":113,"home record":"4 - 1","away record":"4 - 0","points":18,"streak":"1W","form":"2 - 1","average losing margin":6,"average winning margin":14.9,"golden point":0,"close games":3,"day record":"8-2-1","night record":"0-0-0","players used":33},"teamNickName":"Warriors","theme":{"key":"warriors","logoVariants":["badge.png","badge.svg","silhouette.png","silhouette.svg","text.svg"]},"movement":"none","nextTeam":{"fullName":"North Sydney Bears","teamId":500141,"nickName":"Bears","theme":{"key":"north-sydney-bears","logoVariants":["badge.png","badge.svg","silhouette.png"]},"matchCentreUrl":"https:\/\/www.nswrl.com.au\/draw\/intrust-super-premiership\/2017\/round-12\/warriors-vs-bears\/"}},{"stats":{"played":11,"wins":7,"drawn":1,"lost":3,"byes":0,"points for":242,"points against":224,"points difference":18,"home record":"5 - 1","away record":"2 - 2","points":15,"streak":"1W","form":"2 - 2","average losing margin":12,"average winning margin":7.7,"golden point":0,"close games":4,"day record":"7-1-3","night record":"0-0-0","players used":32},"teamNickName":"Mounties","theme":{"key":"mounties","logoVariants":["badge-light.png","badge-light.svg","badge.png","badge.svg","silhouette.png","silhouette.svg"]},"movement":"none","nextTeam":{"fullName":"Wyong Roos","teamId":500140,"nickName":"Roos","theme":{"key":"roos","logoVariants":["badge.png","silhouette.png"]},"matchCentreUrl":"https:\/\/www.nswrl.com.au\/draw\/intrust-super-premiership\/2017\/round-12\/mounties-vs-roos\/"}},{"stats":{"played":11,"wins":6,"drawn":0,"lost":5,"byes":0,"points for":193,"points against":184,"points difference":9,"home record":"0 - 5","away record":"6 - 0","points":12,"streak":"2L","form":"1 - 4","average losing margin":13.2,"average winning margin":12.5,"golden point":0,"close games":3,"day record":"6-0-4","night record":"0-0-1","players used":32},"teamNickName":"Bears","theme":{"key":"north-sydney-bears","logoVariants":["badge.png","badge.svg","silhouette.png"]},"movement":"none","nextTeam":{"fullName":"New Zealand Warriors NSW Cup","teamId":500131,"nickName":"Warriors","theme":{"key":"warriors","logoVariants":["badge.png","badge.svg","silhouette.png","silhouette.svg","text.svg"]},"matchCentreUrl":"https:\/\/www.nswrl.com.au\/draw\/intrust-super-premiership\/2017\/round-12\/warriors-vs-bears\/"}},{"stats":{"played":11,"wins":6,"drawn":0,"lost":5,"byes":0,"points for":238,"points against":262,"points difference":-24,"home record":"3 - 3","away record":"3 - 2","points":12,"streak":"2W","form":"4 - 1","average losing margin":18.8,"average winning margin":11.7,"golden point":0,"close games":2,"day record":"6-0-5","night record":"0-0-0","players used":31},"teamNickName":"Dragons","theme":{"key":"dragons","logoVariants":["badge.png","badge.svg","silhouette.png","silhouette.svg","text.svg"]},"movement":"none","nextTeam":{"teamId":0}},{"stats":{"played":11,"wins":5,"drawn":1,"lost":5,"byes":0,"points for":278,"points against":175,"points difference":103,"home record":"1 - 4","away record":"4 - 1","points":11,"streak":"1W","form":"2 - 2","average losing margin":4.6,"average winning margin":25.2,"golden point":0,"close games":4,"day record":"5-1-3","night record":"0-0-2","players used":32},"teamNickName":"Panthers","theme":{"key":"panthers","logoVariants":["badge-light.png","badge-light.svg","badge.png","badge.svg","silhouette.png","silhouette.svg","text.svg"]},"movement":"none","nextTeam":{"teamId":0}},{"stats":{"played":11,"wins":4,"drawn":1,"lost":6,"byes":0,"points for":194,"points against":210,"points difference":-16,"home record":"1 - 3","away record":"3 - 3","points":9,"streak":"1D","form":"2 - 2","average losing margin":8.7,"average winning margin":9,"golden point":0,"close games":4,"day record":"3-1-6","night record":"1-0-0","players used":29},"teamNickName":"Bulldogs","clubProfileUrl":"\/clubs\/canterbury-bankstown-bulldogs\/","theme":{"key":"bulldogs","logoVariants":["badge.png","badge.svg","silhouette.png","silhouette.svg","text.svg"]},"movement":"up","nextTeam":{"fullName":"Newtown Jets","teamId":500142,"nickName":"Jets","theme":{"key":"jets","logoVariants":["badge.png","badge.svg","silhouette.png","silhouette.svg"]},"matchCentreUrl":"https:\/\/www.nswrl.com.au\/draw\/intrust-super-premiership\/2017\/round-12\/jets-vs-bulldogs\/"}},{"stats":{"played":11,"wins":4,"drawn":0,"lost":7,"byes":0,"points for":219,"points against":224,"points difference":-5,"home record":"2 - 3","away record":"2 - 4","points":8,"streak":"2L","form":"3 - 2","average losing margin":9.1,"average winning margin":14.8,"golden point":0,"close games":5,"day record":"4-0-7","night record":"0-0-0","players used":28},"teamNickName":"Magpies","theme":{"key":"wentworthville","logoVariants":["badge.png","silhouette.png"]},"movement":"down","nextTeam":{"teamId":0}},{"stats":{"played":11,"wins":4,"drawn":0,"lost":7,"byes":0,"points for":216,"points against":263,"points difference":-47,"home record":"0 - 3","away record":"4 - 4","points":8,"streak":"1L","form":"2 - 3","average losing margin":8.1,"average winning margin":2.5,"golden point":0,"close games":7,"day record":"4-0-7","night record":"0-0-0","players used":32},"teamNickName":"Jets","theme":{"key":"jets","logoVariants":["badge.png","badge.svg","silhouette.png","silhouette.svg"]},"movement":"none","nextTeam":{"fullName":"Canterbury-Bankstown Bulldogs NSW Cup","teamId":500138,"nickName":"Bulldogs","theme":{"key":"bulldogs","logoVariants":["badge.png","badge.svg","silhouette.png","silhouette.svg","text.svg"]},"matchCentreUrl":"https:\/\/www.nswrl.com.au\/draw\/intrust-super-premiership\/2017\/round-12\/jets-vs-bulldogs\/"}},{"stats":{"played":11,"wins":4,"drawn":0,"lost":7,"byes":0,"points for":236,"points against":332,"points difference":-96,"home record":"2 - 4","away record":"2 - 3","points":8,"streak":"1L","form":"1 - 4","average losing margin":17.4,"average winning margin":6.5,"golden point":0,"close games":3,"day record":"3-0-7","night record":"1-0-0","players used":34},"teamNickName":"Knights","theme":{"key":"knights","logoVariants":["badge-light.png","badge-light.svg","badge.png","badge.svg","silhouette.png","silhouette.svg","text.svg"]},"movement":"none","nextTeam":{"teamId":0}},{"stats":{"played":11,"wins":3,"drawn":0,"lost":8,"byes":0,"points for":204,"points against":294,"points difference":-90,"home record":"2 - 4","away record":"1 - 4","points":6,"streak":"1W","form":"2 - 3","average losing margin":16.5,"average winning margin":14,"golden point":0,"close games":1,"day record":"3-0-8","night record":"0-0-0","players used":30},"teamNickName":"Sea Eagles","theme":{"key":"blacktown-sea-eagles","logoVariants":["badge.png","badge.svg","silhouette.png","silhouette.svg"]},"movement":"up","nextTeam":{"teamId":0}},{"stats":{"played":11,"wins":3,"drawn":0,"lost":8,"byes":0,"points for":190,"points against":312,"points difference":-122,"home record":"2 - 5","away record":"1 - 3","points":6,"streak":"2L","form":"2 - 3","average losing margin":18.5,"average winning margin":8.7,"golden point":0,"close games":4,"day record":"3-0-8","night record":"0-0-0","players used":32},"teamNickName":"Magpies","theme":{"key":"western-suburbs-magpies","logoVariants":["badge.png","badge.svg","silhouette.png","silhouette.svg"]},"movement":"down","nextTeam":{"teamId":0}}]}