{"id":111,"season":2001,"round":12,"ladder":[{"stats":{"played":12,"wins":9,"drawn":1,"lost":0,"byes":2,"points for":358,"points against":262,"points difference":96,"home record":"0 - 0","away record":"0 - 0","points":23,"streak":"","form":" - ","average losing margin":12,"average winning margin":14,"golden point":0,"close games":2,"day record":"5-0-0","players used":24},"teamNickName":"Knights","clubProfileUrl":"\/clubs\/newcastle-knights\/","theme":{"key":"knights","logoVariants":["badge-light.png","badge-light.svg","badge.png","badge.svg","silhouette.png","silhouette.svg","text.svg"]},"movement":"none","nextTeam":{"fullName":"Penrith Panthers","teamId":500014,"nickName":"Panthers","theme":{"key":"panthers","logoVariants":["badge-light.png","badge-light.svg","badge.png","badge.svg","silhouette.png","silhouette.svg","text.svg"]},"matchCentreUrl":"\/draw\/nrl-premiership\/2001\/round-13\/panthers-v-knights\/"}},{"stats":{"played":12,"wins":8,"drawn":1,"lost":0,"byes":2,"points for":323,"points against":192,"points difference":131,"home record":"0 - 0","away record":"0 - 0","points":21,"streak":"","form":" - ","average losing margin":2,"average winning margin":17,"golden point":0,"close games":4,"day record":"2-1-1","players used":23},"teamNickName":"Broncos","clubProfileUrl":"\/clubs\/brisbane-broncos\/","theme":{"key":"broncos","logoVariants":["badge-light.png","badge-light.svg","badge.png","badge.svg","silhouette.png","silhouette.svg","text.svg"]},"movement":"none","nextTeam":{"fullName":"Northern Eagles","teamId":10053,"nickName":"Eagles","theme":{"key":"eagles"},"matchCentreUrl":"\/draw\/nrl-premiership\/2001\/round-13\/broncos-v-eagles\/"}},{"stats":{"played":12,"wins":7,"drawn":3,"lost":0,"byes":2,"points for":264,"points against":244,"points difference":20,"home record":"0 - 0","away record":"0 - 0","points":21,"streak":"","form":" - ","average losing margin":10,"average winning margin":10,"golden point":0,"close games":2,"day record":"2-0-1","players used":27},"teamNickName":"Bulldogs","clubProfileUrl":"\/clubs\/canterbury-bankstown-bulldogs\/","theme":{"key":"bulldogs","logoVariants":["badge.png","badge.svg","silhouette.png","silhouette.svg","text.svg"]},"movement":"none","nextTeam":{"fullName":"St. George Illawarra Dragons","teamId":500022,"nickName":"Dragons","theme":{"key":"dragons","logoVariants":["badge.png","badge.svg","silhouette.png","silhouette.svg","text.svg"]},"matchCentreUrl":"\/draw\/nrl-premiership\/2001\/round-13\/bulldogs-v-dragons\/"}},{"stats":{"played":12,"wins":7,"drawn":2,"lost":0,"byes":2,"points for":320,"points against":197,"points difference":123,"home record":"0 - 0","away record":"0 - 0","points":20,"streak":"","form":" - ","average losing margin":7,"average winning margin":22,"golden point":0,"close games":2,"day record":"2-0-1","players used":22},"teamNickName":"Eels","clubProfileUrl":"\/clubs\/parramatta-eels\/","theme":{"key":"eels","logoVariants":["badge.png","badge.svg","silhouette.png","silhouette.svg","text.svg"]},"movement":"none","nextTeam":{"fullName":"Sydney Roosters","teamId":500001,"nickName":"Roosters","theme":{"key":"roosters","logoVariants":["badge.png","badge.svg","silhouette.png","silhouette.svg","text.svg"]},"matchCentreUrl":"\/draw\/nrl-premiership\/2001\/round-13\/eels-v-roosters\/"}},{"stats":{"played":12,"wins":7,"drawn":1,"lost":0,"byes":2,"points for":297,"points against":248,"points difference":49,"home record":"0 - 0","away record":"0 - 0","points":19,"streak":"","form":" - ","average losing margin":6,"average winning margin":11,"golden point":0,"close games":3,"day record":"2-1-2","players used":28},"teamNickName":"Roosters","clubProfileUrl":"\/clubs\/sydney-roosters\/","theme":{"key":"roosters","logoVariants":["badge.png","badge.svg","silhouette.png","silhouette.svg","text.svg"]},"movement":"none","nextTeam":{"fullName":"Parramatta Eels","teamId":500031,"nickName":"Eels","theme":{"key":"eels","logoVariants":["badge.png","badge.svg","silhouette.png","silhouette.svg","text.svg"]},"matchCentreUrl":"\/draw\/nrl-premiership\/2001\/round-13\/eels-v-roosters\/"}},{"stats":{"played":12,"wins":6,"drawn":0,"lost":0,"byes":2,"points for":217,"points against":253,"points difference":-36,"home record":"0 - 0","away record":"0 - 0","points":16,"streak":"","form":" - ","average losing margin":14,"average winning margin":8,"golden point":0,"close games":3,"day record":"1-0-3","players used":26},"teamNickName":"Sharks","clubProfileUrl":"\/clubs\/cronulla-sutherland-sharks\/","theme":{"key":"sharks","logoVariants":["badge-light.png","badge-light.svg","badge.png","badge.svg","silhouette.png","silhouette.svg","text.svg"]},"movement":"none","nextTeam":{"fullName":"Wests Tigers","teamId":500023,"nickName":"Wests Tigers","theme":{"key":"wests-tigers","logoVariants":["badge-light.png","badge-light.svg","badge.png","badge.svg","silhouette.png","silhouette.svg","text.svg"]},"matchCentreUrl":"\/draw\/nrl-premiership\/2001\/round-13\/sharks-v-wests-tigers\/"}},{"stats":{"played":12,"wins":6,"drawn":0,"lost":0,"byes":2,"points for":277,"points against":350,"points difference":-73,"home record":"0 - 0","away record":"0 - 0","points":16,"streak":"","form":" - ","average losing margin":18,"average winning margin":6,"golden point":0,"close games":4,"day record":"1-0-2","players used":29},"teamNickName":"Eagles","theme":{"key":"eagles"},"movement":"none","nextTeam":{"teamId":0}},{"stats":{"played":12,"wins":5,"drawn":1,"lost":0,"byes":2,"points for":291,"points against":290,"points difference":1,"home record":"0 - 0","away record":"0 - 0","points":15,"streak":"","form":" - ","average losing margin":13,"average winning margin":18,"golden point":0,"close games":2,"day record":"3-0-3","players used":25},"teamNickName":"Warriors","clubProfileUrl":"\/clubs\/warriors\/","theme":{"key":"warriors","logoVariants":["badge.png","badge.svg","silhouette.png","silhouette.svg","text.svg"]},"movement":"none","nextTeam":{"fullName":"North Queensland Cowboys","teamId":500012,"nickName":"Cowboys","theme":{"key":"cowboys","logoVariants":["badge-light.png","badge-light.svg","badge.png","badge.svg","silhouette.png","silhouette.svg","text.svg"]},"matchCentreUrl":"\/draw\/nrl-premiership\/2001\/round-13\/cowboys-v-warriors\/"}},{"stats":{"played":12,"wins":5,"drawn":0,"lost":0,"byes":2,"points for":336,"points against":297,"points difference":39,"home record":"0 - 0","away record":"0 - 0","points":14,"streak":"","form":" - ","average losing margin":10,"average winning margin":22,"golden point":0,"close games":5,"day record":"2-0-5","players used":23},"teamNickName":"Storm","clubProfileUrl":"\/clubs\/melbourne-storm\/","theme":{"key":"storm","logoVariants":["badge-light.png","badge-light.svg","badge.png","badge.svg","silhouette.png","silhouette.svg","text.svg"]},"movement":"up","nextTeam":{"fullName":"Canberra Raiders","teamId":500013,"nickName":"Raiders","theme":{"key":"raiders","logoVariants":["badge.png","badge.svg","silhouette.png","silhouette.svg","text.svg"]},"matchCentreUrl":"\/draw\/nrl-premiership\/2001\/round-13\/storm-v-raiders\/"}},{"stats":{"played":12,"wins":4,"drawn":1,"lost":0,"byes":2,"points for":302,"points against":278,"points difference":24,"home record":"0 - 0","away record":"0 - 0","points":13,"streak":"","form":" - ","average losing margin":11,"average winning margin":29,"golden point":0,"close games":2,"day record":"3-1-1","players used":25},"teamNickName":"Dragons","clubProfileUrl":"\/clubs\/st-george-illawarra-dragons\/","theme":{"key":"dragons","logoVariants":["badge.png","badge.svg","silhouette.png","silhouette.svg","text.svg"]},"movement":"down","nextTeam":{"fullName":"Canterbury-Bankstown Bulldogs","teamId":500010,"nickName":"Bulldogs","theme":{"key":"bulldogs","logoVariants":["badge.png","badge.svg","silhouette.png","silhouette.svg","text.svg"]},"matchCentreUrl":"\/draw\/nrl-premiership\/2001\/round-13\/bulldogs-v-dragons\/"}},{"stats":{"played":12,"wins":4,"drawn":1,"lost":0,"byes":2,"points for":257,"points against":249,"points difference":8,"home record":"0 - 0","away record":"0 - 0","points":13,"streak":"","form":" - ","average losing margin":5,"average winning margin":12,"golden point":0,"close games":3,"day record":"3-1-4","players used":27},"teamNickName":"Raiders","clubProfileUrl":"\/clubs\/canberra-raiders\/","theme":{"key":"raiders","logoVariants":["badge.png","badge.svg","silhouette.png","silhouette.svg","text.svg"]},"movement":"none","nextTeam":{"fullName":"Melbourne Storm","teamId":500021,"nickName":"Storm","theme":{"key":"storm","logoVariants":["badge-light.png","badge-light.svg","badge.png","badge.svg","silhouette.png","silhouette.svg","text.svg"]},"matchCentreUrl":"\/draw\/nrl-premiership\/2001\/round-13\/storm-v-raiders\/"}},{"stats":{"played":12,"wins":4,"drawn":0,"lost":0,"byes":2,"points for":223,"points against":342,"points difference":-119,"home record":"0 - 0","away record":"0 - 0","points":12,"streak":"","form":" - ","average losing margin":21,"average winning margin":13,"golden point":0,"close games":4,"day record":"3-0-3","players used":28},"teamNickName":"Wests Tigers","clubProfileUrl":"\/clubs\/wests-tigers\/","theme":{"key":"wests-tigers","logoVariants":["badge-light.png","badge-light.svg","badge.png","badge.svg","silhouette.png","silhouette.svg","text.svg"]},"movement":"none","nextTeam":{"fullName":"Cronulla-Sutherland Sharks","teamId":500028,"nickName":"Sharks","theme":{"key":"sharks","logoVariants":["badge-light.png","badge-light.svg","badge.png","badge.svg","silhouette.png","silhouette.svg","text.svg"]},"matchCentreUrl":"\/draw\/nrl-premiership\/2001\/round-13\/sharks-v-wests-tigers\/"}},{"stats":{"played":12,"wins":4,"drawn":0,"lost":0,"byes":2,"points for":223,"points against":391,"points difference":-168,"home record":"0 - 0","away record":"0 - 0","points":12,"streak":"","form":" - ","average losing margin":25,"average winning margin":9,"golden point":0,"close games":1,"day record":"0-0-4","players used":29},"teamNickName":"Panthers","clubProfileUrl":"\/clubs\/penrith-panthers\/","theme":{"key":"panthers","logoVariants":["badge-light.png","badge-light.svg","badge.png","badge.svg","silhouette.png","silhouette.svg","text.svg"]},"movement":"none","nextTeam":{"fullName":"Newcastle Knights","teamId":500003,"nickName":"Knights","theme":{"key":"knights","logoVariants":["badge-light.png","badge-light.svg","badge.png","badge.svg","silhouette.png","silhouette.svg","text.svg"]},"matchCentreUrl":"\/draw\/nrl-premiership\/2001\/round-13\/panthers-v-knights\/"}},{"stats":{"played":12,"wins":2,"drawn":1,"lost":0,"byes":2,"points for":237,"points against":332,"points difference":-95,"home record":"0 - 0","away record":"0 - 0","points":9,"streak":"","form":" - ","average losing margin":11,"average winning margin":9,"golden point":0,"close games":3,"day record":"0-0-3","players used":34},"teamNickName":"Cowboys","clubProfileUrl":"\/clubs\/north-queensland-cowboys\/","theme":{"key":"cowboys","logoVariants":["badge-light.png","badge-light.svg","badge.png","badge.svg","silhouette.png","silhouette.svg","text.svg"]},"movement":"none","nextTeam":{"fullName":"Warriors","teamId":500032,"nickName":"Warriors","theme":{"key":"warriors","logoVariants":["badge.png","badge.svg","silhouette.png","silhouette.svg","text.svg"]},"matchCentreUrl":"\/draw\/nrl-premiership\/2001\/round-13\/cowboys-v-warriors\/"}}]}